archivr/__init__.py
archivr/cli.py
archivr-0.1.3.dist-info/entry_points.txt
archivr-0.1.3.dist-info/WHEEL
archivr-0.1.3.dist-info/METADATA
archivr-0.1.3.dist-info/RECORD
