Metadata-Version: 2.1
Name: archivr
Version: 0.1.3
Summary: 
Author: Sam Wilson
Author-email: skwilson3@crimson.ua.edu
Requires-Python: >=3.9,<4.0
Classifier: Programming Language :: Python :: 3
Classifier: Programming Language :: Python :: 3.9
Requires-Dist: click (>=8.0.1,<9.0.0)
Requires-Dist: tqdm (>=4.62.2,<5.0.0)
